concretefhe_hnp-0.0.10-py3.9-nspkg.pth
concretefhe/hnp/__init__.py
concretefhe/hnp/file.py
concretefhe_hnp-0.0.10.dist-info/LICENSE
concretefhe_hnp-0.0.10.dist-info/METADATA
concretefhe_hnp-0.0.10.dist-info/WHEEL
concretefhe_hnp-0.0.10.dist-info/namespace_packages.txt
concretefhe_hnp-0.0.10.dist-info/top_level.txt
concretefhe_hnp-0.0.10.dist-info/RECORD
